[{"featureShape":[2048],"annotation":"4cutX"},{"annotation":"4cutX","featureShape":[2048]},{"featureShape":[2048],"annotation":"4cutX"},{"annotation":"4cutX","featureShape":[2048]},{"annotation":"4cutX","featureShape":[2048]},{"featureShape":[2048],"annotation":"4cutX"},{"featureShape":[2048],"annotation":"4cutX"},{"annotation":"4cutX","featureShape":[2048]},{"featureShape":[2048],"annotation":"4cutX"},{"annotation":"4cutX","featureShape":[2048]},{"annotation":"4cutX","featureShape":[2048]},{"annotation":"4cutX","featureShape":[2048]},{"annotation":"4cutX","featureShape":[2048]},{"annotation":"4cutX","featureShape":[2048]},{"annotation":"4cutX","featureShape":[2048]},{"featureShape":[2048],"annotation":"4cutX"},{"featureShape":[2048],"annotation":"4cutX"},{"annotation":"4cutX","featureShape":[2048]},{"annotation":"4cutX","featureShape":[2048]},{"annotation":"4cutX","featureShape":[2048]},{"annotation":"4cutX","featureShape":[2048]},{"annotation":"4cutX","featureShape":[2048]},{"featureShape":[2048],"annotation":"4cutX"},{"featureShape":[2048],"annotation":"4cutX"},{"featureShape":[2048],"annotation":"4cutX"},{"featureShape":[2048],"annotation":"4cutX"},{"annotation":"4cutX","featureShape":[2048]},{"featureShape":[2048],"annotation":"4cutX"},{"featureShape":[2048],"annotation":"4cutX"},{"featureShape":[2048],"annotation":"4cutX"},{"annotation":"4cutX","featureShape":[2048]},{"annotation":"4cutX","featureShape":[2048]},{"featureShape":[2048],"annotation":"4cutX"},{"featureShape":[2048],"annotation":"4cutX"},{"annotation":"4cutX","featureShape":[2048]},{"featureShape":[2048],"annotation":"4cutX"},{"annotation":"4cutX","featureShape":[2048]},{"featureShape":[2048],"annotation":"4cutX"},{"featureShape":[2048],"annotation":"4cutX"},{"featureShape":[2048],"annotation":"4cutX"},{"featureShape":[2048],"annotation":"4cutX"},{"featureShape":[2048],"annotation":"4cutX"},{"featureShape":[2048],"annotation":"4cutX"},{"annotation":"4cutX","featureShape":[2048]},{"featureShape":[2048],"annotation":"4cutX"},{"featureShape":[2048],"annotation":"4cutX"},{"annotation":"4cutX","featureShape":[2048]},{"featureShape":[2048],"annotation":"4cutX"},{"featureShape":[2048],"annotation":"4cutX"},{"featureShape":[2048],"annotation":"4cutX"},{"annotation":"4cutX","featureShape":[2048]},{"annotation":"4cutX","featureShape":[2048]},{"featureShape":[2048],"annotation":"4cutX"},{"featureShape":[2048],"annotation":"4cutX"},{"featureShape":[2048],"annotation":"4cutX"},{"featureShape":[2048],"annotation":"4cutX"},{"featureShape":[2048],"annotation":"4cutX"},{"featureShape":[2048],"annotation":"4cutX"},{"featureShape":[2048],"annotation":"4cutX"},{"featureShape":[2048],"annotation":"4cutX"},{"annotation":"4cutX","featureShape":[2048]},{"featureShape":[2048],"annotation":"4cutX"},{"featureShape":[2048],"annotation":"4cutX"},{"annotation":"4cutX","featureShape":[2048]},{"featureShape":[2048],"annotation":"4cutX"},{"featureShape":[2048],"annotation":"4cutX"},{"featureShape":[2048],"annotation":"4cutX"},{"annotation":"4cutX","featureShape":[2048]},{"featureShape":[2048],"annotation":"4cutX"},{"featureShape":[2048],"annotation":"4cutX"},{"featureShape":[2048],"annotation":"4cutX"},{"annotation":"4cutX","featureShape":[2048]},{"annotation":"4cutX","featureShape":[2048]},{"featureShape":[2048],"annotation":"4cutX"},{"featureShape":[2048],"annotation":"4cutX"},{"annotation":"4cutX","featureShape":[2048]},{"annotation":"4cutX","featureShape":[2048]},{"annotation":"4cutX","featureShape":[2048]},{"annotation":"4cutX","featureShape":[2048]},{"featureShape":[2048],"annotation":"4cutX"},{"annotation":"4cutX","featureShape":[2048]},{"featureShape":[2048],"annotation":"4cutX"},{"featureShape":[2048],"annotation":"4cutX"},{"annotation":"4cutX","featureShape":[2048]},{"featureShape":[2048],"annotation":"4cutX"},{"featureShape":[2048],"annotation":"4cutX"},{"annotation":"4cutX","featureShape":[2048]},{"featureShape":[2048],"annotation":"4cutX"},{"annotation":"4cutX","featureShape":[2048]},{"annotation":"4cutX","featureShape":[2048]},{"annotation":"4cutX","featureShape":[2048]},{"annotation":"4cutX","featureShape":[2048]},{"featureShape":[2048],"annotation":"4cutX"},{"featureShape":[2048],"annotation":"4cutX"},{"featureShape":[2048],"annotation":"4cutX"},{"annotation":"4cutX","featureShape":[2048]},{"featureShape":[2048],"annotation":"4cutX"},{"featureShape":[2048],"annotation":"4cutX"},{"annotation":"4cutX","featureShape":[2048]},{"annotation":"4cutX","featureShape":[2048]},{"featureShape":[2048],"annotation":"4cutX"},{"featureShape":[2048],"annotation":"4cutX"},{"annotation":"4cutX","featureShape":[2048]},{"annotation":"4cutX","featureShape":[2048]},{"annotation":"4cutX","featureShape":[2048]},{"annotation":"4cutX","featureShape":[2048]},{"annotation":"4cutX","featureShape":[2048]},{"featureShape":[2048],"annotation":"4cutX"},{"featureShape":[2048],"annotation":"4cutX"},{"featureShape":[2048],"annotation":"4cutX"},{"annotation":"4cutX","featureShape":[2048]},{"annotation":"4cutX","featureShape":[2048]},{"annotation":"4cutX","featureShape":[2048]},{"featureShape":[2048],"annotation":"4cut"},{"featureShape":[2048],"annotation":"4cut"},{"annotation":"4cutX","featureShape":[2048]},{"featureShape":[2048],"annotation":"4cut"},{"annotation":"4cutX","featureShape":[2048]},{"annotation":"4cut","featureShape":[2048]},{"annotation":"4cutX","featureShape":[2048]},{"featureShape":[2048],"annotation":"4cut"},{"annotation":"4cut","featureShape":[2048]},{"annotation":"4cut","featureShape":[2048]},{"featureShape":[2048],"annotation":"4cut"},{"annotation":"4cut","featureShape":[2048]},{"annotation":"4cut","featureShape":[2048]},{"featureShape":[2048],"annotation":"4cut"},{"featureShape":[2048],"annotation":"4cut"},{"annotation":"4cut","featureShape":[2048]},{"featureShape":[2048],"annotation":"4cut"},{"annotation":"4cut","featureShape":[2048]},{"annotation":"4cut","featureShape":[2048]},{"annotation":"4cut","featureShape":[2048]},{"featureShape":[2048],"annotation":"4cut"},{"featureShape":[2048],"annotation":"4cut"},{"featureShape":[2048],"annotation":"4cut"},{"annotation":"4cut","featureShape":[2048]},{"annotation":"4cut","featureShape":[2048]},{"annotation":"4cut","featureShape":[2048]},{"featureShape":[2048],"annotation":"4cut"},{"annotation":"4cut","featureShape":[2048]},{"annotation":"4cut","featureShape":[2048]},{"featureShape":[2048],"annotation":"4cut"},{"featureShape":[2048],"annotation":"4cut"},{"featureShape":[2048],"annotation":"4cut"},{"annotation":"4cut","featureShape":[2048]},{"featureShape":[2048],"annotation":"4cut"},{"featureShape":[2048],"annotation":"4cut"},{"annotation":"4cut","featureShape":[2048]},{"annotation":"4cut","featureShape":[2048]},{"annotation":"4cut","featureShape":[2048]},{"featureShape":[2048],"annotation":"4cut"},{"annotation":"4cut","featureShape":[2048]},{"annotation":"4cut","featureShape":[2048]},{"annotation":"4cut","featureShape":[2048]},{"annotation":"4cut","featureShape":[2048]},{"featureShape":[2048],"annotation":"4cut"},{"annotation":"4cut","featureShape":[2048]},{"annotation":"4cut","featureShape":[2048]},{"annotation":"4cut","featureShape":[2048]},{"annotation":"4cut","featureShape":[2048]},{"annotation":"4cut","featureShape":[2048]},{"featureShape":[2048],"annotation":"4cut"},{"annotation":"4cut","featureShape":[2048]},{"annotation":"4cut","featureShape":[2048]},{"annotation":"4cut","featureShape":[2048]},{"annotation":"4cut","featureShape":[2048]},{"featureShape":[2048],"annotation":"4cut"},{"featureShape":[2048],"annotation":"4cut"},{"annotation":"4cut","featureShape":[2048]},{"featureShape":[2048],"annotation":"4cut"},{"featureShape":[2048],"annotation":"4cut"},{"featureShape":[2048],"annotation":"4cut"},{"featureShape":[2048],"annotation":"4cut"},{"annotation":"4cut","featureShape":[2048]},{"featureShape":[2048],"annotation":"4cut"},{"annotation":"4cut","featureShape":[2048]},{"annotation":"4cut","featureShape":[2048]},{"featureShape":[2048],"annotation":"4cut"},{"annotation":"4cut","featureShape":[2048]},{"annotation":"4cut","featureShape":[2048]},{"featureShape":[2048],"annotation":"4cut"},{"featureShape":[2048],"annotation":"4cut"},{"annotation":"4cut","featureShape":[2048]},{"featureShape":[2048],"annotation":"4cut"},{"featureShape":[2048],"annotation":"4cut"},{"featureShape":[2048],"annotation":"4cut"},{"featureShape":[2048],"annotation":"4cut"},{"annotation":"4cut","featureShape":[2048]},{"annotation":"4cut","featureShape":[2048]},{"annotation":"4cut","featureShape":[2048]},{"annotation":"4cut","featureShape":[2048]},{"featureShape":[2048],"annotation":"4cut"},{"annotation":"4cut","featureShape":[2048]},{"featureShape":[2048],"annotation":"4cut"},{"featureShape":[2048],"annotation":"4cut"},{"featureShape":[2048],"annotation":"4cut"},{"annotation":"4cut","featureShape":[2048]},{"featureShape":[2048],"annotation":"4cut"},{"featureShape":[2048],"annotation":"4cut"},{"featureShape":[2048],"annotation":"4cut"},{"featureShape":[2048],"annotation":"4cut"},{"featureShape":[2048],"annotation":"4cut"},{"featureShape":[2048],"annotation":"4cut"},{"annotation":"4cut","featureShape":[2048]},{"annotation":"4cut","featureShape":[2048]},{"featureShape":[2048],"annotation":"4cut"},{"annotation":"4cut","featureShape":[2048]},{"featureShape":[2048],"annotation":"4cut"},{"annotation":"4cut","featureShape":[2048]},{"annotation":"4cut","featureShape":[2048]},{"featureShape":[2048],"annotation":"4cut"},{"annotation":"4cut","featureShape":[2048]},{"annotation":"4cut","featureShape":[2048]}]